[
  {
    "id": "f1",
    "name": "opacity",
    "min": "0",
    "max": "100",
    "value": "100",
    "unit": "%"
  },
  {
    "id": "f2",
    "name": "blur",
    "min": "0",
    "max": "100",
    "value": "0",
    "unit": "px"
  },
  {
    "id": "f3",
    "name": "brightness",
    "min": "0",
    "max": "200",
    "value": "100",
    "unit": "%"
  },
  {
    "id": "f4",
    "name": "contrast",
    "min": "0",
    "max": "200",
    "value": "100",
    "unit": "%"
  },
  {
    "id": "f5",
    "name": "grayscale",
    "min": "0",
    "max": "100",
    "value": "0",
    "unit": "%"
  },
  {
    "id": "f6",
    "name": "hue-rotate",
    "min": "0",
    "max": "100",
    "value": "0",
    "unit": "deg"
  },
  {
    "id": "f7",
    "name": "saturate",
    "min": "0",
    "max": "200",
    "value": "100",
    "unit": "%"
  },
  {
    "id": "f8",
    "name": "sepia",
    "min": "0",
    "max": "100",
    "value": "0",
    "unit": "%"
  }
]
